LICENSE
MANIFEST.in
README.md
setup.cfg
setup.py
src/clibmet/Makefile
src/clibmet/libdoa/libdoa.c
src/clibmet/libxcorr/libxcorr.c
src/clibmet/libxcorr/libxcorr.h
src/metecho/__init__.py
src/metecho/version.py
src/metecho.egg-info/PKG-INFO
src/metecho.egg-info/SOURCES.txt
src/metecho.egg-info/dependency_links.txt
src/metecho.egg-info/entry_points.txt
src/metecho.egg-info/requires.txt
src/metecho.egg-info/top_level.txt
src/metecho/cli/__init__.py
src/metecho/cli/commands.py
src/metecho/cli/convert.py
src/metecho/cli/event_search.py
src/metecho/coordinates/__init__.py
src/metecho/coordinates/frames.py
src/metecho/coordinates/hammer_aitoff.py
src/metecho/data/__init__.py
src/metecho/data/converters.py
src/metecho/data/data_store.py
src/metecho/data/eiscat_drf.py
src/metecho/data/eiscat_matlab.py
src/metecho/data/mu.py
src/metecho/data/raw_data.py
src/metecho/estimation/__init__.py
src/metecho/estimation/scam.py
src/metecho/events/__init__.py
src/metecho/events/conf.py
src/metecho/events/event.py
src/metecho/events/event_search.py
src/metecho/events/event_select.py
src/metecho/events/filters.py
src/metecho/events/search_objects.py
src/metecho/generalized_matched_filter/__init__.py
src/metecho/generalized_matched_filter/xcorr.py
src/metecho/meteor_model/__init__.py
src/metecho/meteor_model/ablation.py
src/metecho/meteor_model/linear_motion.py
src/metecho/meteor_model/model.py
src/metecho/meteoroid_streams/__init__.py
src/metecho/meteoroid_streams/iau.py
src/metecho/meteoroid_streams/radiant.py
src/metecho/noise/__init__.py
src/metecho/noise/calc_noise.py
src/metecho/physics/__init__.py
src/metecho/physics/material_classification.py
src/metecho/plot/__init__.py
src/metecho/plot/general.py
src/metecho/plot/generalized_matched_filter.py
src/metecho/plot/orbits.py
src/metecho/plot/radiants.py
src/metecho/plot/raw_data.py
src/metecho/signal_model/__init__.py
src/metecho/signal_model/phase_coding.py
src/metecho/signal_model/sampler.py
src/metecho/signal_model/signal_generator.py
src/metecho/signal_model/target_effects.py
src/metecho/simulation/MU_radar_head_echo.py
src/metecho/simulation/__init__.py
src/metecho/simulation/sensor_simulation.py
src/metecho/tools/__init__.py
