Metadata-Version: 2.4
Name: metecho
Version: 0.0.5
Summary: Radar meteor analysis in Python and C
Home-page: https://github.com/danielk333/metecho
Author: Daniel Kastinen, Kenneth Kullbrandt
Author-email: daniel.kastinen@irf.se
License: MIT
Classifier: Programming Language :: Python :: 3.7
Classifier: License :: OSI Approved :: GNU General Public License v3 (GPLv3)
Classifier: Operating System :: OS Independent
Classifier: Intended Audience :: Science/Research
Classifier: Development Status :: 4 - Beta
Requires-Python: >=3.7
License-File: LICENSE
Requires-Dist: h5py>=3.4.0
Requires-Dist: matplotlib>=2.2.2
Requires-Dist: numpy>=1.14.3
Requires-Dist: scipy>=1.1.0
Requires-Dist: tabulate>=0.8.7
Requires-Dist: tqdm>=4.46.0
Requires-Dist: pyant>=0.11.0
Requires-Dist: requests>=2.28.2
Provides-Extra: develop
Requires-Dist: pytest>=6.2.5; extra == "develop"
Requires-Dist: sphinx>=4.2.0; extra == "develop"
Requires-Dist: flake8>=4.0.1; extra == "develop"
Requires-Dist: wheel>=0.37.0; extra == "develop"
Requires-Dist: build>=0.7.0; extra == "develop"
Requires-Dist: twine>=3.4.2; extra == "develop"
Requires-Dist: coverage>=6.0.2; extra == "develop"
Requires-Dist: sphinx-gallery>=0.3.1; extra == "develop"
Requires-Dist: matplotlib>=3.5.1; extra == "develop"
Requires-Dist: nbsphinx>=0.8.8; extra == "develop"
Requires-Dist: ipykernel>=6.9.1; extra == "develop"
Requires-Dist: radon>=5.1.0; extra == "develop"
Requires-Dist: m2r2>=0.3.2; extra == "develop"
Requires-Dist: setuptools>=57.4.0; extra == "develop"
Requires-Dist: numpydoc>=1.2; extra == "develop"
Requires-Dist: black>=23.7.0; extra == "develop"
Provides-Extra: mpi
Requires-Dist: mpi4py>=3.1.1; extra == "mpi"
Provides-Extra: extra
Requires-Dist: pandas>=1.4.0; extra == "extra"
Requires-Dist: ablate>=0.1.0; extra == "extra"
Provides-Extra: all
Requires-Dist: mpi4py>=3.1.1; extra == "all"
Requires-Dist: pandas>=1.4.0; extra == "all"
Requires-Dist: ablate>=0.1.0; extra == "all"
Dynamic: license-file
